{
  "type": "summoner",
  "version": "14.9.1",
  "data": {
    "SummonerFlash": {
      "id": "SummonerFlash",
      "name": "Flash",
      "description": "Teleports your champion a short distance toward your cursor's location.",
      "image": { "full": "SummonerFlash.png" }
    },
    "SummonerDot": {
      "id": "SummonerDot",
      "name": "Ignite",
      "description": "Ignites target enemy champion, dealing 70-410 true damage over 5 seconds and reducing healing effects.",
      "image": { "full": "SummonerDot.png" }
    },
    "SummonerTeleport": {
      "id": "SummonerTeleport",
      "name": "Teleport",
      "description": "After channeling for 4 seconds, teleports your champion to target allied structure.",
      "image": { "full": "SummonerTeleport.png" }
    },
    "SummonerSmite": {
      "id": "SummonerSmite",
      "name": "Smite",
      "description": "Deals 600-1200 true damage to target monster or minion.",
      "image": { "full": "SummonerSmite.png" }
    },
    "SummonerHeal": {
      "id": "SummonerHeal",
      "name": "Heal",
      "description": "Restores 80-318 Health and grants 30% Movement Speed for 1 second to you and target allied champion.",
      "image": { "full": "SummonerHeal.png" }
    },
    "SummonerExhaust": {
      "id": "SummonerExhaust",
      "name": "Exhaust",
      "description": "Exhausts target enemy champion, reducing their Movement Speed by 30% and their damage dealt by 35% for 3 seconds.",
      "image": { "full": "SummonerExhaust.png" }
    }
  }
}